chrome_extension/__init__.py
chrome_extension/package_storage.py
chrome_extension-1.0.1.dist-info/LICENSE
chrome_extension-1.0.1.dist-info/METADATA
chrome_extension-1.0.1.dist-info/WHEEL
chrome_extension-1.0.1.dist-info/RECORD
