Metadata-Version: 2.3
Name: chrome_extension
Version: 1.0.1
Summary: Chrome Extension Python allows you to easily integrate Chrome extensions in web automation frameworks like Botasaurus, Selenium, and Playwright.
License: MIT
Author: Carlos Mateus
Author-email: carlosmatateumateus@gmail.com
Requires-Python: >=3.9,<4.0
Classifier: Programming Language :: Python :: 3
Classifier: Operating System :: OS Independent
Requires-Dist: build (>=1.2.2.post1,<2.0.0)
Requires-Dist: twine (>=6.1.0,<7.0.0)
Project-URL: Homepage, https://github.com/kamajus/chrome_extension
Project-URL: Issues, https://github.com/kamajus/chrome_extension/issues
